MANIFEST.in
README.md
setup.cfg
setup.py
subsync/__init__.py
subsync/__main__.py
subsync/ffmpeg.py
subsync/log.py
subsync/main.py
subsync/media.py
subsync/net.py
subsync/subsync.pb
subsync/version.py
subsync.egg-info/PKG-INFO
subsync.egg-info/SOURCES.txt
subsync.egg-info/dependency_links.txt
subsync.egg-info/not-zip-safe
subsync.egg-info/requires.txt
subsync.egg-info/top_level.txt
subsync/bin/subsync