Metadata-Version: 1.1
Name: subsync
Version: 0.1.2
Summary: Synchronize your subtitles with mahcine learning
Home-page: https://github.com/tympanix/subsync
Author: tympanix
Author-email: tympanix@gmail.com
License: MIT
Keywords: subtitle synchronize machine learning
Platform: Independent
Classifier: License :: OSI Approved :: MIT License
Classifier: Programming Language :: Python :: 3.6
Classifier: Topic :: Multimedia :: Sound/Audio :: Analysis
Classifier: Topic :: Multimedia :: Sound/Audio :: Speech
